BeginnersbookJavaIoJiaochengChuyiFix1/README.md
BeginnersbookJavaIoJiaochengChuyiFix1/__init__.py
BeginnersbookJavaIoJiaochengChuyiFix1/__main__.py
BeginnersbookJavaIoJiaochengChuyiFix1/file.epub
BeginnersbookJavaIoJiaochengChuyiFix1/index.html
BeginnersbookJavaIoJiaochengChuyiFix1/css/__init__.py
BeginnersbookJavaIoJiaochengChuyiFix1/css/annotations.css
BeginnersbookJavaIoJiaochengChuyiFix1/css/main.css
BeginnersbookJavaIoJiaochengChuyiFix1/css/normalize.css
BeginnersbookJavaIoJiaochengChuyiFix1/css/popup.css
BeginnersbookJavaIoJiaochengChuyiFix1/font/__init__.py
BeginnersbookJavaIoJiaochengChuyiFix1/font/fontello.eot
BeginnersbookJavaIoJiaochengChuyiFix1/font/fontello.svg
BeginnersbookJavaIoJiaochengChuyiFix1/font/fontello.ttf
BeginnersbookJavaIoJiaochengChuyiFix1/font/fontello.woff
BeginnersbookJavaIoJiaochengChuyiFix1/img/__init__.py
BeginnersbookJavaIoJiaochengChuyiFix1/img/annotator-glyph-sprite.png
BeginnersbookJavaIoJiaochengChuyiFix1/img/annotator-icon-sprite.png
BeginnersbookJavaIoJiaochengChuyiFix1/img/apple-touch-icon.png
BeginnersbookJavaIoJiaochengChuyiFix1/img/cancelfullscreen.png
BeginnersbookJavaIoJiaochengChuyiFix1/img/close.png
BeginnersbookJavaIoJiaochengChuyiFix1/img/fullscreen.png
BeginnersbookJavaIoJiaochengChuyiFix1/img/loader.gif
BeginnersbookJavaIoJiaochengChuyiFix1/img/menu-icon.png
BeginnersbookJavaIoJiaochengChuyiFix1/img/save.png
BeginnersbookJavaIoJiaochengChuyiFix1/img/saved.png
BeginnersbookJavaIoJiaochengChuyiFix1/img/settings-s.png
BeginnersbookJavaIoJiaochengChuyiFix1/img/settings.png
BeginnersbookJavaIoJiaochengChuyiFix1/img/star.png
BeginnersbookJavaIoJiaochengChuyiFix1/js/__init__.py
BeginnersbookJavaIoJiaochengChuyiFix1/js/epub.js
BeginnersbookJavaIoJiaochengChuyiFix1/js/epub.min.js
BeginnersbookJavaIoJiaochengChuyiFix1/js/epub.min.map
BeginnersbookJavaIoJiaochengChuyiFix1/js/hooks.min.js
BeginnersbookJavaIoJiaochengChuyiFix1/js/hooks.min.map
BeginnersbookJavaIoJiaochengChuyiFix1/js/reader.js
beginnersbook_java_io_jiaocheng_chuyi_fix1-2025.3.23.0.dist-info/METADATA
beginnersbook_java_io_jiaocheng_chuyi_fix1-2025.3.23.0.dist-info/WHEEL
beginnersbook_java_io_jiaocheng_chuyi_fix1-2025.3.23.0.dist-info/entry_points.txt
beginnersbook_java_io_jiaocheng_chuyi_fix1-2025.3.23.0.dist-info/top_level.txt
beginnersbook_java_io_jiaocheng_chuyi_fix1-2025.3.23.0.dist-info/RECORD
